setup.py
dm/__init__.py
dm.zopepatches.formlib.egg-info/PKG-INFO
dm.zopepatches.formlib.egg-info/SOURCES.txt
dm.zopepatches.formlib.egg-info/dependency_links.txt
dm.zopepatches.formlib.egg-info/namespace_packages.txt
dm.zopepatches.formlib.egg-info/not-zip-safe
dm.zopepatches.formlib.egg-info/top_level.txt
dm/zopepatches/__init__.py
dm/zopepatches/formlib/README.txt
dm/zopepatches/formlib/VERSION.txt
dm/zopepatches/formlib/__init__.py
dm/zopepatches/formlib/form.py
dm/zopepatches/formlib/multiselection.py
dm/zopepatches/formlib/patch.py
dm/zopepatches/formlib/widget.py