Metadata-Version: 1.0
Name: dm.zopepatches.formlib
Version: 1.0.1
Summary: Work around problems/weaknesses in 'zope.formlib' and the widgets in 'zope.app.form'.
Home-page: http://pypi.python.org/pypi/dm.zopepatches.formlib
Author: Dieter Maurer
Author-email: dieter@handshake.de
License: BSD
Keywords: application development web formlib multiple selection error handling
Platform: UNKNOWN
Classifier: Development Status :: 5 - Production/Stable
Classifier: Intended Audience :: Developers
Classifier: License :: OSI Approved :: Zope Public License
Classifier: Framework :: Zope2
Classifier: Operating System :: OS Independent
Classifier: Programming Language :: Python
Classifier: Topic :: Utilities
